Lab2/A/Lab2_4_bit_BLS_behavioral.v
module Lab2_4_bit_BLS_behavioral (input [3:0] A, B, input bin, output reg [3:0] D, output reg bout);
    reg [0:3] p, g;
    reg b0, b1, b2;
    always @(*) 
        begin
            g[0] = !A[0] && B[0];
            g[1] = !A[1] && B[1];
            g[2] = !A[2] && B[2];
            g[3] = !A[3] && B[3];
            p[0] = !A[0] || B[0];
            p[1] = !A[1] || B[1];
            p[2] = !A[2] || B[2];
            p[3] = !A[3] || B[3];
            b0 = g[0] || (p[0] && bin);
            b1 = g[1] || (p[1] && b0);
            b2 = g[2] || (p[2] && b1);
            bout = g[3] || (p[3] && b2);
            D[0] = A[0] ^ B[0] ^ bin;
            D[1] = A[1] ^ B[1] ^ b0;
            D[2] = A[2] ^ B[2] ^ b1;
            D[3] = A[3] ^ B[3] ^ b2;
        end
endmodule

Lab2/A/Lab2_4_bit_BLS_dataflow.v
module Lab2_4_bit_BLS_dataflow (input [3:0] A, B, input bin, output [3:0] D, output bout);
    wire [0:3] p, g;
    assign  g[0] = !A[0] && B[0],
            g[1] = !A[1] && B[1],
            g[2] = !A[2] && B[2],
            g[3] = !A[3] && B[3];
    assign  p[0] = !A[0] || B[0],
            p[1] = !A[1] || B[1],
            p[2] = !A[2] || B[2],
            p[3] = !A[3] || B[3];
    
    wire b0, b1, b2;
    assign  D[0] = A[0] ^ B[0] ^ bin,
            D[1] = A[1] ^ B[1] ^ b0,
            D[2] = A[2] ^ B[2] ^ b1,
            D[3] = A[3] ^ B[3] ^ b2;

    assign  b0 = g[0] || (p[0] && bin),
            b1 = g[1] || (p[1] && b0),
            b2 = g[2] || (p[2] && b1),
            bout = g[3] || (p[3] && b2);
endmodule

Lab2/A/Lab2_4_bit_BLS_gatelevel.v
module Lab2_4_bit_BLS_gatelevel (input [3:0] A, B, input bin, output [3:0] D, output
bout);
    wire w0, w1, w2, w3;
    not a0_not(w0, A[0]), a1_not(w1, A[1]), a2_not(w2, A[2]), a3_not(w3, A[3]);
    wire p0, g0, p1, g1, p2, g2, p3, g3;
    and #(2) G0(g0, w0, B[0]),
             G1(g1, w1, B[1]),
             G2(g2, w2, B[2]),
             G3(g3, w3, B[3]);
    or  #(2) P0(p0, w0, B[0]),
             P1(p1, w1, B[1]),
             P2(p2, w2, B[2]),
             P3(p3, w3, B[3]);

    wire t0, t1, t2, t3;
    wire b0, b1, b2;        // borrow out
    xor #(4) x0(t0, A[0], B[0]), x1(t1, A[1], B[1]), x2(t2, A[2], B[2]), x3(t3, A[3], B[3]);
    xor #(4) d0(D[0], t0, bin), d1(D[1], t1, b0), d2(D[2], t2, b1), d3(D[3], t3, b2);

    wire t4, t5, t6, t7;
    and #(2) pb0(t4, p0, bin), pb1(t5, p1, b0), pb2(t6, p2, b1), pb3(t7, p3, b2);
    or #(2) B0(b0, g0, t4), B1(b1, g1, t5), B2(b2, g2, t6), B3(bout, g3, t7);
endmodule

Lab2/A/t_Lab2_4_bit_sub.v
module t_Lab2_4_bit_sub();
    reg [3:0] A, B;
    reg bin;
    wire [3:0] D, D_g, D_d, D_b;
    wire bout, bout_g, bout_d, bout_b;

    //Lab2_4_bit_RBS RBS(A, B, bin, D, bout);
    Lab2_4_bit_BLS_gatelevel BLS_gatelevel(A, B, bin, D_g, bout_g);
    Lab2_4_bit_BLS_dataflow BLS_dataflow(A, B, bin, D_d, bout_d);
    Lab2_4_bit_BLS_behavioral BLS_behavioral(A, B, bin, D_b, bout_b);

    initial #400 $finish;
    initial begin
        A = 4'b0000; B = 4'b1100; bin = 1;
        #50 A = 4'b0001; B = 4'b0010; bin = 1;
        #50 A = 4'b0011; B = 4'b0110; bin = 1;
        #50 A = 4'b0101; B = 4'b1011; bin = 0;
        #50 A = 4'b0111; B = 4'b1010; bin = 1;
        #50 A = 4'b1000; B = 4'b0001; bin = 0;
        #50 A = 4'b1011; B = 4'b0110; bin = 0;
        #50 A = 4'b1111; B = 4'b1111; bin = 1;
    end

    initial begin
		$dumpfile("t_Lab2_4_bit_BLS.vcd");
		$dumpvars;
	end
endmodule

Lab2/A/t_Lab2_4_bit_BLS.vcd
$date
	Sat May 07 03:11:56 2022
$end
$version
	Icarus Verilog
$end
$timescale
	1s
$end
$scope module t_Lab2_4_bit_sub $end
$var wire 1 ! bout_g $end
$var wire 1 " bout_d $end
$var wire 1 # bout_b $end
$var wire 4 $ D_g [3:0] $end
$var wire 4 % D_d [3:0] $end
$var wire 4 & D_b [3:0] $end
$var reg 4 ' A [3:0] $end
$var reg 4 ( B [3:0] $end
$var reg 1 ) bin $end
$scope module BLS_behavioral $end
$var wire 4 * A [3:0] $end
$var wire 4 + B [3:0] $end
$var wire 1 ) bin $end
$var reg 4 , D [3:0] $end
$var reg 1 - b0 $end
$var reg 1 . b1 $end
$var reg 1 / b2 $end
$var reg 1 # bout $end
$var reg 4 0 g [0:3] $end
$var reg 4 1 p [0:3] $end
$upscope $end
$scope module BLS_dataflow $end
$var wire 4 2 A [3:0] $end
$var wire 4 3 B [3:0] $end
$var wire 1 4 b0 $end
$var wire 1 5 b1 $end
$var wire 1 6 b2 $end
$var wire 1 ) bin $end
$var wire 1 " bout $end
$var wire 4 7 p [0:3] $end
$var wire 4 8 g [0:3] $end
$var wire 4 9 D [3:0] $end
$upscope $end
$scope module BLS_gatelevel $end
$var wire 4 : A [3:0] $end
$var wire 4 ; B [3:0] $end
$var wire 1 < b0 $end
$var wire 1 = b1 $end
$var wire 1 > b2 $end
$var wire 1 ) bin $end
$var wire 1 ! bout $end
$var wire 1 ? g0 $end
$var wire 1 @ g1 $end
$var wire 1 A g2 $end
$var wire 1 B g3 $end
$var wire 1 C p0 $end
$var wire 1 D p1 $end
$var wire 1 E p2 $end
$var wire 1 F p3 $end
$var wire 1 G t0 $end
$var wire 1 H t1 $end
$var wire 1 I t2 $end
$var wire 1 J t3 $end
$var wire 1 K t4 $end
$var wire 1 L t5 $end
$var wire 1 M t6 $end
$var wire 1 N t7 $end
$var wire 1 O w0 $end
$var wire 1 P w1 $end
$var wire 1 Q w2 $end
$var wire 1 R w3 $end
$var wire 4 S D [3:0] $end
$upscope $end
$upscope $end
$enddefinitions $end
#0
$dumpvars
bx S
1R
1Q
1P
1O
xN
xM
xL
xK
xJ
xI
xH
xG
xF
xE
xD
xC
xB
xA
x@
x?
x>
x=
x<
b1100 ;
b0 :
b11 9
b11 8
b1111 7
16
15
14
b1100 3
b0 2
b1111 1
b11 0
1/
1.
1-
b11 ,
b1100 +
b0 *
1)
b1100 (
b0 '
b11 &
b11 %
bx $
1#
1"
x!
$end
#2
0?
0@
1A
1B
1C
1D
1E
1F
#4
1>
1!
1K
0G
0H
1I
1J
#6
1N
1<
#8
1L
b0xx1 $
b0xx1 S
#10
1=
b0x11 $
b0x11 S
#12
1M
#14
b11 $
b11 S
#50
04
b1110 %
b1110 9
b100 8
b111 7
0O
b1110 &
b1110 ,
0-
b111 1
b100 0
b10 (
b10 +
b10 3
b10 ;
b1 '
b1 *
b1 2
b1 :
#52
0C
1@
0A
0B
#54
0K
1H
0I
0J
1G
#56
0<
#58
0L
b1110 $
b1110 S
#100
05
b1100 %
b1100 9
b10 8
0P
b1100 &
b1100 ,
0.
b10 0
b110 (
b110 +
b110 3
b110 ;
b11 '
b11 *
b11 2
b11 :
#102
0@
1A
#104
0=
1I
0H
#106
0M
#108
b1100 $
b1100 S
#150
15
06
b101 8
b1101 7
1P
0Q
b1010 %
b1010 9
b1010 &
b1010 ,
0/
1.
b1101 1
b101 0
0)
b1011 (
b1011 +
b1011 3
b1011 ;
b101 '
b101 *
b101 2
b101 :
#152
1@
0A
1B
1C
0E
#154
1=
0>
0G
1J
1H
b1101 $
b1101 S
#156
0N
#158
b1010 $
b1010 S
#200
05
04
b101 7
b1 8
0P
b1100 %
b1100 9
b1100 &
b1100 ,
0.
b101 1
b1 0
1)
b1010 (
b1010 +
b1010 3
b1010 ;
b111 '
b111 *
b111 2
b111 :
#202
0@
0C
1K
#204
0=
0K
1<
1G
0H
b1011 $
b1011 S
#206
0<
1L
#208
0L
1=
b1110 $
b1110 S
#210
0=
b1100 $
b1100 S
#250
16
15
14
0"
b1000 8
b1110 7
1O
1P
1Q
0R
b111 %
b111 9
b111 &
b111 ,
0#
1/
1.
1-
b1110 1
b1000 0
0)
b1 (
b1 +
b1 3
b1 ;
b1000 '
b1000 *
b1000 2
b1000 :
#252
1E
1?
0B
1C
0F
#254
1<
0!
0I
b1101 $
b1101 S
#256
1L
#258
1=
b1011 $
b1011 S
#260
1M
#262
1>
b1111 $
b1111 S
#266
b111 $
b111 S
#300
05
04
b101 %
b101 9
b10 8
b110 7
0O
0P
b101 &
b101 ,
0.
0-
b110 1
b10 0
b110 (
b110 +
b110 3
b110 ;
b1011 '
b1011 *
b1011 2
b1011 :
#302
0?
1A
0C
#304
0<
1I
#306
0L
#308
0=
b1 $
b1 S
#310
0M
#312
b101 $
b101 S
#350
1"
15
14
16
b1111 7
b0 8
0Q
b1111 %
b1111 9
b1111 &
b1111 ,
1#
1.
1-
b1111 1
b0 0
1)
b1111 (
b1111 +
b1111 3
b1111 ;
b1111 '
b1111 *
b1111 2
b1111 :
#352
0A
1C
1F
#354
0>
1K
1N
0G
0J
0I
b100 $
b100 S
#356
0N
1<
1!
#358
0!
1L
b1 $
b1 S
#360
1=
b11 $
b11 S
#362
1M
#364
1>
b111 $
b111 S
#366
1N
#368
1!
b1111 $
b1111 S
