Lab2/A/Lab2_half_sub_gatelevel.v
module Lab2_half_sub_gatelevel(input a, b, output diff, bout);
    xor #(4) g1(diff, a, b);
    wire a_not;
    not  g2(a_not, a);
    and #(2) g3(bout, a_not, b);
endmodule

Lab2/A/t_Lab2_half_sub.v
module t_Lab2_half_sub();
    wire diff, bout;
    reg a, b;
    Lab2_half_sub_gatelevel M1(a, b, diff, bout);
    
    initial #80 $finish;

    initial begin
        a=0; b=0;
        #20 a=0; b=1; 
        #20 a=1; b=0; 
        #20 a=1; b=1; 
    end

    initial begin
		$dumpfile("t_Lab2_half_sub.vcd");
		$dumpvars;
	end

endmodule

Lab2/A/t_Lab2_half_sub.vcd
$date
	Fri May 06 03:02:45 2022
$end
$version
	Icarus Verilog
$end
$timescale
	1s
$end
$scope module t_Lab2_half_sub $end
$var wire 1 ! diff $end
$var wire 1 " bout $end
$var reg 1 # a $end
$var reg 1 $ b $end
$scope module M1 $end
$var wire 1 # a $end
$var wire 1 % a_not $end
$var wire 1 $ b $end
$var wire 1 " bout $end
$var wire 1 ! diff $end
$upscope $end
$upscope $end
$enddefinitions $end
#0
$dumpvars
1%
0$
0#
x"
x!
$end
#2
0"
#4
0!
#20
1$
#22
1"
#24
1!
#40
0%
0$
1#
#42
0"
#60
1$
#64
0!
