Lab2/B/Lab2_converter_4bit_behavioral.v
module Lab2_converter_4bit_behavioral (input [3:0] E, output reg [3:0] B, output reg v);
    always @(*)
        begin
            B[3] = (E[3] && E[2]) || (E[3] && E[1] && E[0]);
            B[2] = !(E[2] ^ (E[1] && E[0]));
            B[1] = E[1] ^ E[0];
            B[0] = !E[0];
            v = (E[3] ^ E[2]) || (E[3] ^ (E[1] && E[0]));
        end
endmodule

Lab2/B/Lab2_converter_4bit_dataflow.v
module Lab2_converter_4bit_dataflow (input [3:0] E, output [3:0] B, output v);
    assign  B[3] = (E[3] && E[2]) || (E[3] && E[1] && E[0]),
            B[2] = !(E[2] ^ (E[1] && E[0])),
            B[1] = E[1] ^ E[0],
            B[0] = !E[0],
            v = (E[3] ^ E[2]) || (E[3] ^ (E[1] && E[0]));

endmodule

Lab2/B/Lab2_converter_4bit_gatelevel.v
module Lab2_converter_4bit_gatelevel (input [3:0] E, output [3:0] B, output v);
    wire e3e2, e3e1, e3e1e0;
    and a1(e3e2, E[3], E[2]), a2(e3e1, E[3], E[1]), a3(e3e1e0, e3e1, E[0]);
    or b3(B[3], e3e2, e3e1e0);

    wire e1e0;
    and a4(e1e0, E[1], E[0]);
    xnor b2(B[2], E[2], e1e0);

    xor b1(B[1], E[1], E[0]);

    not b0(B[0], E[0]);

    wire w1, w2;
    xor v1(w1, E[3], E[2]), v2(w2, E[3], e1e0);
    or v_gate(v, w1, w2);

endmodule

Lab2/B/t_Lab2_converter_4bit.v
module t_Lab2_converter_4bit();
    reg [3:0] E;
    wire [3:0] B;
    wire v;

    Lab2_converter_4bit_gatelevel g(E, B, v);
    Lab2_converter_4bit_dataflow d(E, B, v);
    Lab2_converter_4bit_behavioral b(E, B, v);

    initial #160 $finish;
    initial begin
        E = 4'b0000;
        repeat(15) #10 E = E + 1'b1;
    end
    
    initial begin
		$dumpfile("t_Lab2_converter_4bit.vcd");
		$dumpvars;
	end

endmodule

Lab2/B/t_Lab2_converter_4bit.vcd
$date
	Sat May 07 20:59:32 2022
$end
$version
	Icarus Verilog
$end
$timescale
	1s
$end
$scope module t_Lab2_converter_4bit $end
$var wire 4 ! B [3:0] $end
$var wire 1 " v $end
$var reg 4 # E [3:0] $end
$scope module b $end
$var wire 4 $ E [3:0] $end
$var reg 4 % B [3:0] $end
$var reg 1 & v $end
$upscope $end
$scope module d $end
$var wire 4 ' B [3:0] $end
$var wire 4 ( E [3:0] $end
$var wire 1 " v $end
$upscope $end
$scope module g $end
$var wire 4 ) B [3:0] $end
$var wire 4 * E [3:0] $end
$var wire 1 + e1e0 $end
$var wire 1 , e3e1 $end
$var wire 1 - e3e1e0 $end
$var wire 1 . e3e2 $end
$var wire 1 " v $end
$var wire 1 / w1 $end
$var wire 1 0 w2 $end
$upscope $end
$upscope $end
$enddefinitions $end
#0
$dumpvars
00
0/
0.
0-
0,
0+
b0 *
b101 )
b0 (
b101 '
0&
b101 %
b0 $
b0 #
0"
b101 !
$end
#10
b110 %
b110 !
b110 '
b110 )
b1 #
b1 $
b1 (
b1 *
#20
b111 %
b111 !
b111 '
b111 )
b10 #
b10 $
b10 (
b10 *
#30
10
1+
1"
1&
b0 %
b0 !
b0 '
b0 )
b11 #
b11 $
b11 (
b11 *
#40
00
0+
1/
b1 %
b1 !
b1 '
b1 )
b100 #
b100 $
b100 (
b100 *
#50
b10 %
b10 !
b10 '
b10 )
b101 #
b101 $
b101 (
b101 *
#60
b11 %
b11 !
b11 '
b11 )
b110 #
b110 $
b110 (
b110 *
#70
10
1+
b100 %
b100 !
b100 '
b100 )
b111 #
b111 $
b111 (
b111 *
#80
0+
10
b101 %
b101 !
b101 '
b101 )
b1000 #
b1000 $
b1000 (
b1000 *
#90
b110 %
b110 !
b110 '
b110 )
b1001 #
b1001 $
b1001 (
b1001 *
#100
1,
b111 %
b111 !
b111 '
b111 )
b1010 #
b1010 $
b1010 (
b1010 *
#110
00
1-
1+
b1000 %
b1000 !
b1000 '
b1000 )
b1011 #
b1011 $
b1011 (
b1011 *
#120
10
1"
1.
0,
0-
0+
0/
b1001 %
b1001 !
b1001 '
b1001 )
b1100 #
b1100 $
b1100 (
b1100 *
#130
b1010 %
b1010 !
b1010 '
b1010 )
b1101 #
b1101 $
b1101 (
b1101 *
#140
1,
b1011 %
b1011 !
b1011 '
b1011 )
b1110 #
b1110 $
b1110 (
b1110 *
#150
00
1-
1+
0"
0&
b1100 %
b1100 !
b1100 '
b1100 )
b1111 #
b1111 $
b1111 (
b1111 *
