Lab1/2022_Lab1/B/Lab1_UDP.v
module Lab1_UDP(input x,y,z, output m);
    wire w;
    or   G1(w, x, y);
    and  G2(m, w, z);
endmodule

Lab1/2022_Lab1/B/Lab1_gatelevel_UDP.v
module Lab1_gatelevel_UDP(F, A, B, C, D);
    input A, B, C, D;
    output F;
    wire B_not, D_not, w0, w1, w2;
    not nb(B_not, B), nd(D_not, D);

    Lab1_UDP UDP1(A, B_not, C, w0);
    and G1(w1, B, C);
    Lab1_UDP UDP2(w1, D_not, A, w2);
    or G2(F, w0, w2);
endmodule

Lab1/2022_Lab1/B/Lab1_dataflow.v
module Lab1_dataflow(F, A, B, C, D);
    input   A, B, C, D;
    output  F;
    wire [0:5] w;

    assign w[0] = A || !B;
    assign w[1] = w[0] && C;
    assign w[2] = B && C;
    assign w[3] = w[2] || !D;
    assign w[4] = w[3] && A;
    assign F = w[1] || w[4];

endmodule

Lab1/2022_Lab1/B/Lab1_gatelevel.v
module Lab1_gatelevel(F, A, B, C, D);
    output F;
    input A, B, C, D;
    wire B_not, D_not, w0, w1, w2, w3, w4;
    not nb(B_not, B);
    not nd(D_not, D);
    or G1(w0, A, B_not);
    and G2(w1, w0, C);
    and G3(w2, B, C);
    or G4(w3, w2, D_not);
    and G5(w4, w3, A);
    or G6(F, w1, w4);
endmodule

Lab1/2022_Lab1/B/t_Lab1.v
module t_Lab1();
    wire F;
    reg  [3:0] T;

    Lab1_gatelevel L1(F, T[3], T[2], T[1], T[0]);
    Lab1_dataflow L2(F, T[3], T[2], T[1], T[0]);
    Lab1_gatelevel_UDP L3(F, T[3], T[2], T[1], T[0]);

    initial begin
        T = 4'b0000;
        repeat(15)  #10 T = T + 1'b1;
    end

    initial begin
		$dumpfile("t_Lab1.vcd");
		$dumpvars;
	end

endmodule

Lab1/2022_Lab1/B/t_Lab1.vcd
$date
	Wed Apr 20 22:35:47 2022
$end
$version
	Icarus Verilog
$end
$timescale
	1s
$end
$scope module t_Lab1 $end
$var wire 1 ! F $end
$var reg 4 " T [3:0] $end
$scope module L1 $end
$var wire 1 # A $end
$var wire 1 $ B $end
$var wire 1 % B_not $end
$var wire 1 & C $end
$var wire 1 ' D $end
$var wire 1 ( D_not $end
$var wire 1 ! F $end
$var wire 1 ) w0 $end
$var wire 1 * w1 $end
$var wire 1 + w2 $end
$var wire 1 , w3 $end
$var wire 1 - w4 $end
$upscope $end
$scope module L2 $end
$var wire 1 . A $end
$var wire 1 / B $end
$var wire 1 0 C $end
$var wire 1 1 D $end
$var wire 1 ! F $end
$var wire 6 2 w [0:5] $end
$upscope $end
$scope module L3 $end
$var wire 1 3 A $end
$var wire 1 4 B $end
$var wire 1 5 B_not $end
$var wire 1 6 C $end
$var wire 1 7 D $end
$var wire 1 8 D_not $end
$var wire 1 ! F $end
$var wire 1 9 w1 $end
$var wire 1 : w2 $end
$var wire 1 ; w0 $end
$scope module UDP1 $end
$var wire 1 ; m $end
$var wire 1 < w $end
$var wire 1 3 x $end
$var wire 1 5 y $end
$var wire 1 6 z $end
$upscope $end
$scope module UDP2 $end
$var wire 1 : m $end
$var wire 1 = w $end
$var wire 1 9 x $end
$var wire 1 8 y $end
$var wire 1 3 z $end
$upscope $end
$upscope $end
$upscope $end
$enddefinitions $end
#0
$dumpvars
1=
1<
0;
0:
09
18
07
06
15
04
03
b10010z 2
01
00
0/
0.
0-
1,
0+
0*
1)
1(
0'
0&
1%
0$
0#
b0 "
0!
$end
#10
0,
0=
0(
b10000z 2
08
1'
11
17
b1 "
#20
1,
1!
1=
1*
1(
b11010z 2
1;
18
1&
0'
10
01
16
07
b10 "
#30
0,
0=
0(
b11000z 2
08
1'
11
17
b11 "
#40
0)
1,
0<
0!
1=
0%
0*
1(
b10z 2
05
0;
18
1$
0&
0'
1/
00
01
14
06
07
b100 "
#50
0,
0=
0(
b0z 2
08
1'
11
17
b101 "
#60
1,
1=
1+
1(
b110z 2
19
18
1&
0'
10
01
16
07
b110 "
#70
0(
08
1'
11
17
b111 "
#80
1!
1)
1-
1%
0+
1(
b10011z 2
1<
1:
15
09
18
1#
0$
0&
0'
1.
0/
00
01
13
04
06
07
b1000 "
#90
0!
0-
0:
0,
0=
0(
b10000z 2
08
1'
11
17
b1001 "
#100
1-
1:
1,
1!
1=
1*
1(
b11011z 2
1;
18
1&
0'
10
01
16
07
b1010 "
#110
0-
0:
0,
0=
0(
b11000z 2
08
1'
11
17
b1011 "
#120
1-
1:
1,
1!
1=
0%
0*
1(
b10011z 2
05
0;
18
1$
0&
0'
1/
00
01
14
06
07
b1100 "
#130
0!
0-
0:
0,
0=
0(
b10000z 2
08
1'
11
17
b1101 "
#140
1-
1:
1,
1!
1=
1*
1+
1(
b11111z 2
19
1;
18
1&
0'
10
01
16
07
b1110 "
#150
0(
08
1'
11
17
b1111 "
