Lab3/D_ff_AR.v
module D_ff_AR (input D, clock, reset, output Q);
    reg Q;
    always @(posedge clock, negedge reset)
        if(!reset) Q <= 1'b0;
        else Q <= D;
endmodule

Lab3/Lab3_Sequence_Recognizer_structure.v
module Lab3_Sequence_Recognizer_structure (input x, clock, reset, output z);
    wire DA, DB, DC;
    wire A, B, C;
    assign DA = (~C & x) | (A & ~x) | (B & C & ~x);
    assign DB = (A & B) | (B & ~x) | (C & x) | (A & C);
    assign DC = (~A & ~B & ~x) | (~A & ~C & ~x) | (~B & ~C & ~x);
    assign z = ~A & B & ~C & ~x;

    D_ff_AR FFA(DA, clock, reset, A);
    D_ff_AR FFB(DB, clock, reset, B);
    D_ff_AR FFC(DC, clock, reset, C);

endmodule

Lab3/Lab3_Sequence_Recognizer_state_diagram.v
module Lab3_Sequence_Recognizer_state_diagram (input x, clock, reset, output z);
    reg[2:0] state, next_state;
    parameter s0 = 3'b000, s1 = 3'b001, s2 = 3'b010, s3 = 3'b011, s4 = 3'b100, s5 = 3'b101, s6 = 3'b110;

    always @(posedge clock, negedge reset)
        if(reset == 0) state <= s0;
        else state <= next_state;
    
    always @(state, x)
        case(state)
            s0: if(x) next_state = s4; else next_state = s1;
            s1: if(x) next_state = s2; else next_state = s1;
            s2: if(x) next_state = s4; else next_state = s3;
            s3: if(x) next_state = s2; else next_state = s6;
            s4: if(x) next_state = s4; else next_state = s5;
            s5: if(x) next_state = s2; else next_state = s6;
            s6: if(x) next_state = s6; else next_state = s6;
        endcase
    
    assign z = (state==s2) && (x==0);
endmodule

Lab3/t_Lab3_Sequence_Recognizer.v
module t_Lab3_Sequence_Recognizer();
    reg x, clock, reset;
    wire z1, z2;

    Lab3_Sequence_Recognizer_state_diagram m1(x, clock, reset, z1);
    Lab3_Sequence_Recognizer_structure m2(x, clock, reset, z2);

    initial #200 $finish;
    initial begin
        clock = 0;
        forever #5 clock = ~clock;
    end

    initial fork
        reset = 0;
        #2 reset = 1;
        #87 reset = 0;
        #89 reset = 1;
        x = 1;
        #10 x = 0;
        #20 x = 1;
        #30 x = 0;          // output 1
        #40 x = 1;
        #50 x = 0;          // output 1
        #60 x = 0;          
        #70 x = 1;
        #80 x = 0;          // output 0
        #86 x = 1;
        #100 x = 0;
        #110 x = 1;
        #120 x = 0;         // output 1
        #130 x = 1;
        #140 x = 1;
        #150 x = 1;
    join

    initial begin
        $dumpfile("t_Lab3_Sequence_Recognizer.vcd");
        $dumpvars;
    end
endmodule

Lab3/t_Lab3_Sequence_Recognizer.vcd
$date
	Sat Jun 04 02:58:03 2022
$end
$version
	Icarus Verilog
$end
$timescale
	1s
$end
$scope module t_Lab3_Sequence_Recognizer $end
$var wire 1 ! z2 $end
$var wire 1 " z1 $end
$var reg 1 # clock $end
$var reg 1 $ reset $end
$var reg 1 % x $end
$scope module m1 $end
$var wire 1 # clock $end
$var wire 1 $ reset $end
$var wire 1 % x $end
$var wire 1 " z $end
$var reg 3 & next_state [2:0] $end
$var reg 3 ' state [2:0] $end
$upscope $end
$scope module m2 $end
$var wire 1 ( DA $end
$var wire 1 ) DB $end
$var wire 1 * DC $end
$var wire 1 # clock $end
$var wire 1 $ reset $end
$var wire 1 % x $end
$var wire 1 ! z $end
$var wire 1 + C $end
$var wire 1 , B $end
$var wire 1 - A $end
$scope module FFA $end
$var wire 1 ( D $end
$var wire 1 # clock $end
$var wire 1 $ reset $end
$var reg 1 - Q $end
$upscope $end
$scope module FFB $end
$var wire 1 ) D $end
$var wire 1 # clock $end
$var wire 1 $ reset $end
$var reg 1 , Q $end
$upscope $end
$scope module FFC $end
$var wire 1 * D $end
$var wire 1 # clock $end
$var wire 1 $ reset $end
$var reg 1 + Q $end
$upscope $end
$upscope $end
$upscope $end
$enddefinitions $end
#0
$dumpvars
0-
0,
0+
0*
0)
1(
b0 '
b100 &
1%
0$
0#
0"
0!
$end
#2
1$
#5
1-
b100 '
1#
#10
1*
b101 &
0#
0%
#15
0*
1)
b110 &
b101 '
1+
1#
#20
0(
b10 &
0#
1%
#25
1(
0)
b100 &
0+
1,
0-
b10 '
1#
#30
1)
1*
0(
1!
b11 &
1"
0#
0%
#35
0*
0!
1(
b110 &
0"
b11 '
1+
1#
#40
0(
b10 &
0#
1%
#45
1(
0)
b100 &
0+
b10 '
1#
#50
1)
1*
0(
1!
b11 &
1"
0#
0%
#55
0*
0!
1(
b110 &
0"
b11 '
1+
1#
#60
0#
#65
0+
1-
b110 '
1#
#70
0#
1%
#75
1#
#80
0#
0%
#85
1#
#86
1%
#87
0)
b100 &
b0 '
0-
0,
0$
#89
1$
#90
0#
#95
1-
b100 '
1#
#100
1*
b101 &
0#
0%
#105
0*
1)
b110 &
b101 '
1+
1#
#110
0(
b10 &
0#
1%
#115
1(
0)
b100 &
0+
1,
0-
b10 '
1#
#120
1)
1*
0(
1!
b11 &
1"
0#
0%
#125
0*
0!
1(
b110 &
0"
b11 '
1+
1#
#130
0(
b10 &
0#
1%
#135
1(
0)
b100 &
0+
b10 '
1#
#140
0#
#145
b100 '
1-
0,
1#
