Lab3/Lab3_SR_Latch_gatelevel.v
module Lab3_SR_Latch_gatelevel (input S, R, output Q, Qb);
    nor #(10) g1(Q, R, Qb);
    nor #(10) g2(Qb, Q, S);
endmodule

Lab3/Lab3_NE_Dff_gatelevel.v
module Lab3_NE_Dff_gatelevel(input D, clock, output Q, Qb);
    wire w1, w2, w3, x1;
    Lab3_SR_Latch_gatelevel SR1(clock, w2, x1, w3);
    nor #(10) G1(w1, w3, clock, w2);
    nor #(10) G2(w2, w1, D);
    Lab3_SR_Latch_gatelevel SR2(w1, w3, Q, Qb);
endmodule

Lab3/t_Lab3_NE_Dff_gatelevel.v
module t_Lab3_NE_Dff_gatelevel();
    reg D, clock;
    wire Q, Qb;

    Lab3_NE_Dff_gatelevel NE_DFF(D, clock, Q, Qb);
    initial #320 $finish;
    initial begin clock = 0; forever #20 clock = ~clock; end
    initial fork
        D = 0;
        #55 D = 1;
        #97 D = 0;
        #137 D = 1;
        #165 D = 0;
        #195 D = 1;
        #255 D = 0;
    join
    initial begin
        $dumpfile("t_Lab3_NE_Dff_gatelevel.vcd");
        $dumpvars;
    end

endmodule

Lab3/t_Lab3_NE_Dff_gatelevel.vcd
$date
	Fri Jun 03 21:18:35 2022
$end
$version
	Icarus Verilog
$end
$timescale
	1s
$end
$scope module t_Lab3_NE_Dff_gatelevel $end
$var wire 1 ! Qb $end
$var wire 1 " Q $end
$var reg 1 # D $end
$var reg 1 $ clock $end
$scope module NE_DFF $end
$var wire 1 # D $end
$var wire 1 $ clock $end
$var wire 1 % w1 $end
$var wire 1 & w2 $end
$var wire 1 ' x1 $end
$var wire 1 ( w3 $end
$var wire 1 ! Qb $end
$var wire 1 " Q $end
$scope module SR1 $end
$var wire 1 ' Q $end
$var wire 1 ( Qb $end
$var wire 1 & R $end
$var wire 1 $ S $end
$upscope $end
$scope module SR2 $end
$var wire 1 " Q $end
$var wire 1 ! Qb $end
$var wire 1 ( R $end
$var wire 1 % S $end
$upscope $end
$upscope $end
$upscope $end
$enddefinitions $end
#0
$dumpvars
x(
x'
x&
x%
0$
0#
x"
x!
$end
#20
1$
#30
0%
0(
#40
1&
0$
#50
0'
x(
#55
1#
#60
1(
1$
#65
0&
#70
0"
0(
#80
1!
x"
1'
0$
#90
0"
x!
1%
#97
0#
#100
x"
0!
1$
#110
1"
0%
#120
1&
0$
#130
0'
#137
1#
#140
1(
1$
#147
0&
#150
0"
0(
#160
1!
1"
1'
0$
#165
0#
#170
0"
0!
1%
#180
1"
1$
#190
0%
#195
1#
#200
0$
#210
1%
#220
1$
#230
0%
#240
0$
#250
1%
#255
0#
#260
1$
#270
0%
#280
1&
0$
#290
0'
#300
1(
1$
#310
0"
0(
#320
1!
1"
0$
